license.txt
setup.py
AdderUz/__init__.py
AdderUz/adder.py
AdderUz/number.py
AdderUz.egg-info/PKG-INFO
AdderUz.egg-info/SOURCES.txt
AdderUz.egg-info/dependency_links.txt
AdderUz.egg-info/top_level.txt