Metadata-Version: 2.1
Name: AdderUz
Version: 0.0.1
Summary: by this package you can add numbers easyly
Author: Umidjon
License-File: license.txt
